langgraph_enterprise_sdk/__init__.py
langgraph_enterprise_sdk/__version__.py
langgraph_enterprise_sdk/a2a/__init__.py
langgraph_enterprise_sdk/a2a/adapter.py
langgraph_enterprise_sdk/a2a/delegation.py
langgraph_enterprise_sdk/a2a/discovery.py
langgraph_enterprise_sdk/a2a/routing.py
langgraph_enterprise_sdk/a2a/security.py
langgraph_enterprise_sdk/api/__init__.py
langgraph_enterprise_sdk/api/config.py
langgraph_enterprise_sdk/api/edges.py
langgraph_enterprise_sdk/api/graph.py
langgraph_enterprise_sdk/api/node.py
langgraph_enterprise_sdk/api/runnable.py
langgraph_enterprise_sdk/api/state.py
langgraph_enterprise_sdk/connectors/__init__.py
langgraph_enterprise_sdk/connectors/cloud.py
langgraph_enterprise_sdk/connectors/kafka.py
langgraph_enterprise_sdk/connectors/neo4j.py
langgraph_enterprise_sdk/connectors/opensearch.py
langgraph_enterprise_sdk/connectors/postgres.py
langgraph_enterprise_sdk/errors/__init__.py
langgraph_enterprise_sdk/errors/execution.py
langgraph_enterprise_sdk/errors/persistence.py
langgraph_enterprise_sdk/errors/security.py
langgraph_enterprise_sdk/errors/validation.py
langgraph_enterprise_sdk/execution/__init__.py
langgraph_enterprise_sdk/execution/cancellation.py
langgraph_enterprise_sdk/execution/executor.py
langgraph_enterprise_sdk/execution/lifecycle.py
langgraph_enterprise_sdk/execution/retries.py
langgraph_enterprise_sdk/execution/scheduler.py
langgraph_enterprise_sdk/governance/__init__.py
langgraph_enterprise_sdk/governance/approvals.py
langgraph_enterprise_sdk/governance/audit.py
langgraph_enterprise_sdk/governance/compliance.py
langgraph_enterprise_sdk/governance/data_retention.py
langgraph_enterprise_sdk/governance/quotas.py
langgraph_enterprise_sdk/graph_store/__init__.py
langgraph_enterprise_sdk/graph_store/base.py
langgraph_enterprise_sdk/graph_store/cypher.py
langgraph_enterprise_sdk/graph_store/neo4j.py
langgraph_enterprise_sdk/graph_store/reasoning.py
langgraph_enterprise_sdk/graph_store/schema.py
langgraph_enterprise_sdk-0.1.2.dist-info/licenses/LICENSE
langgraph_enterprise_sdk-0.1.2.dist-info/METADATA
langgraph_enterprise_sdk-0.1.2.dist-info/WHEEL
langgraph_enterprise_sdk-0.1.2.dist-info/top_level.txt
langgraph_enterprise_sdk-0.1.2.dist-info/RECORD
