Metadata-Version: 2.4
Name: langgraph-enterprise-sdk
Version: 0.1.2
Summary: Enterprise-grade Agent Platform SDK built on LangGraph principles (TOON + ZAD)
Author-email: Ganesh Kinkar Giri <k.ganeshgiri@gmail.com>
License:                                  Apache License
Project-URL: Homepage, https://github.com/your-org/langgraph-enterprise-sdk
Project-URL: Documentation, https://github.com/your-org/langgraph-enterprise-sdk/docs
Project-URL: Repository, https://github.com/your-org/langgraph-enterprise-sdk
Project-URL: Issues, https://github.com/your-org/langgraph-enterprise-sdk/issues
Keywords: langgraph,agentic-ai,enterprise-ai,multi-agent,a2a,mcp,llm,rag,governance,platform-engineering
Classifier: Development Status :: 4 - Beta
Classifier: Intended Audience :: Developers
Classifier: Intended Audience :: Information Technology
Classifier: Intended Audience :: System Administrators
Classifier: License :: OSI Approved :: Apache Software License
Classifier: Programming Language :: Python :: 3
Classifier: Programming Language :: Python :: 3.10
Classifier: Programming Language :: Python :: 3.11
Classifier: Programming Language :: Python :: 3.12
Classifier: Topic :: Software Development :: Libraries
Classifier: Topic :: Software Development :: Libraries :: Application Frameworks
Classifier: Topic :: System :: Distributed Computing
Classifier: Topic :: Scientific/Engineering :: Artificial Intelligence
Requires-Python: >=3.10
License-File: LICENSE
Requires-Dist: fastapi>=0.110
Requires-Dist: pydantic>=2.6
Requires-Dist: typing-extensions>=4.10
Requires-Dist: tenacity>=8.2
Requires-Dist: structlog>=24.1
Requires-Dist: prometheus-client>=0.20
Requires-Dist: opentelemetry-api>=1.24
Requires-Dist: httpx>=0.27
Requires-Dist: websockets>=12.0
Requires-Dist: python-dotenv>=1.0
Provides-Extra: postgres
Requires-Dist: psycopg2-binary>=2.9; extra == "postgres"
Provides-Extra: redis
Requires-Dist: redis>=5.0; extra == "redis"
Provides-Extra: neo4j
Requires-Dist: neo4j>=5.18; extra == "neo4j"
Provides-Extra: opensearch
Requires-Dist: opensearch-py>=2.4; extra == "opensearch"
Provides-Extra: aws
Requires-Dist: boto3>=1.34; extra == "aws"
Provides-Extra: llm-openai
Requires-Dist: openai>=1.14; extra == "llm-openai"
Provides-Extra: llm-azure
Requires-Dist: openai>=1.14; extra == "llm-azure"
Provides-Extra: llm-anthropic
Requires-Dist: anthropic>=0.21; extra == "llm-anthropic"
Provides-Extra: llm-ollama
Requires-Dist: ollama>=0.1; extra == "llm-ollama"
Provides-Extra: llm-llama-cpp
Requires-Dist: llama-cpp-python>=0.2.55; extra == "llm-llama-cpp"
Provides-Extra: llm-groq
Requires-Dist: groq>=0.9.0; extra == "llm-groq"
Provides-Extra: all-llms
Requires-Dist: openai>=1.14; extra == "all-llms"
Requires-Dist: anthropic>=0.21; extra == "all-llms"
Requires-Dist: ollama>=0.1; extra == "all-llms"
Requires-Dist: llama-cpp-python>=0.2.55; extra == "all-llms"
Requires-Dist: groq>=0.9.0; extra == "all-llms"
Provides-Extra: a2a
Requires-Dist: a2a-python-sdk>=0.1.0; extra == "a2a"
Provides-Extra: mcp
Provides-Extra: security
Requires-Dist: python-jose>=3.3; extra == "security"
Requires-Dist: cryptography>=42.0; extra == "security"
Provides-Extra: dev
Requires-Dist: pytest>=8.1; extra == "dev"
Requires-Dist: pytest-asyncio>=0.23; extra == "dev"
Requires-Dist: pytest-cov>=4.1; extra == "dev"
Requires-Dist: ruff>=0.4; extra == "dev"
Requires-Dist: black>=24.3; extra == "dev"
Requires-Dist: mypy>=1.9; extra == "dev"
Requires-Dist: pre-commit>=3.6; extra == "dev"
Provides-Extra: enterprise
Requires-Dist: langgraph-enterprise-sdk[aws,neo4j,opensearch,postgres,redis]; extra == "enterprise"
Requires-Dist: langgraph-enterprise-sdk[all-llms]; extra == "enterprise"
Requires-Dist: langgraph-enterprise-sdk[a2a,mcp,security]; extra == "enterprise"
Dynamic: license-file
